{
  "generated_at": "2026-07-23T18:50:34.523798+00:00",
  "items": [
    {
      "ts": "2026-07-23T18:49:43.349000+00:00",
      "time": "02:49 PM ET",
      "type": "alert",
      "message": "@here \ud83d\udd34 **BTC \u2014 BROKE BELOW S2 $64832.85** Current: **$64821.77** | Strength: 4/5 \u2014 Fibonacci 0.650 retracement + psychological level + lies within re"
    },
    {
      "ts": "2026-07-23T18:48:38.856000+00:00",
      "time": "02:48 PM ET",
      "type": "analysis",
      "message": "@here \ud83d\udfe2 **BTC \u2014 BROKE ABOVE S2 $64832.85** Current: **$64840.97** | Strength: 4/5 \u2014 Fibonacci 0.650 retracement + psychological level + lies within re"
    },
    {
      "ts": "2026-07-23T18:45:30.784000+00:00",
      "time": "02:45 PM ET",
      "type": "analysis",
      "message": "@here \ud83d\udfe2 **MSTR \u2014 BROKE ABOVE S2 $94.63** Current: **$94.72** | Strength: 5/5 |"
    },
    {
      "ts": "2026-07-23T18:45:06.722000+00:00",
      "time": "02:45 PM ET",
      "type": "alert",
      "message": "@here \ud83d\udea8\ud83d\udea8\ud83d\udea8\ud83d\udea8\ud83d\udea8\ud83d\udea8\ud83d\udea8\ud83d\udea8\ud83d\udea8\ud83d\udea8\ud83d\udea8\ud83d\udea8\ud83d\udea8\ud83d\udea8\ud83d\udea8 \u26d4 **STOP-LOSS HIT \u2014 BTC** \u26d4 \ud83d\udea8\ud83d\udea8\ud83d\udea8\ud83d\udea8\ud83d\udea8\ud83d\udea8\ud83d\udea8\ud83d\udea8\ud83d\udea8\ud83d\udea8\ud83d\udea8\ud83d\udea8\ud83d\udea8\ud83d\udea8\ud83d\udea8  **BTC DROPPED -20.4% \u2014 STOP TRIGGERED** Entry: $81,388 \u2192 Now: **$64,761**  \u23f0 **YOU "
    },
    {
      "ts": "2026-07-23T18:33:40.752000+00:00",
      "time": "02:33 PM ET",
      "type": "analysis",
      "message": "@here \ud83d\udfe2 **MU \u2014 BROKE ABOVE R1 $993.35** Current: **$993.41** | Strength: 5/5 |"
    },
    {
      "ts": "2026-07-23T18:30:07.395000+00:00",
      "time": "02:30 PM ET",
      "type": "alert",
      "message": "@here \ud83d\udd34\ud83d\udd34\ud83d\udd34\ud83d\udd34\ud83d\udd34\ud83d\udd34\ud83d\udd34\ud83d\udd34\ud83d\udd34\ud83d\udd34\ud83d\udd34\ud83d\udd34\ud83d\udd34\ud83d\udd34\ud83d\udd34 \u26a1 **AUTO-SELL EXECUTED \u2014 BTC** \u26a1 \ud83d\udd34\ud83d\udd34\ud83d\udd34\ud83d\udd34\ud83d\udd34\ud83d\udd34\ud83d\udd34\ud83d\udd34\ud83d\udd34\ud83d\udd34\ud83d\udd34\ud83d\udd34\ud83d\udd34\ud83d\udd34\ud83d\udd34  **BTC HAS BEEN SOLD \u2014 NO RESPONSE RECEIVED** Sold at: **$64,760** | P&L: **-20"
    },
    {
      "ts": "2026-07-23T18:15:06.301000+00:00",
      "time": "02:15 PM ET",
      "type": "alert",
      "message": "@here \ud83d\udea8\ud83d\udea8\ud83d\udea8\ud83d\udea8\ud83d\udea8\ud83d\udea8\ud83d\udea8\ud83d\udea8\ud83d\udea8\ud83d\udea8\ud83d\udea8\ud83d\udea8\ud83d\udea8\ud83d\udea8\ud83d\udea8 \u26d4 **STOP-LOSS HIT \u2014 BTC** \u26d4 \ud83d\udea8\ud83d\udea8\ud83d\udea8\ud83d\udea8\ud83d\udea8\ud83d\udea8\ud83d\udea8\ud83d\udea8\ud83d\udea8\ud83d\udea8\ud83d\udea8\ud83d\udea8\ud83d\udea8\ud83d\udea8\ud83d\udea8  **BTC DROPPED -20.5% \u2014 STOP TRIGGERED** Entry: $81,388 \u2192 Now: **$64,671**  \u23f0 **YOU "
    },
    {
      "ts": "2026-07-23T18:13:29.203000+00:00",
      "time": "02:13 PM ET",
      "type": "analysis",
      "message": "@here \ud83d\udfe2 **MU \u2014 BROKE ABOVE R2 $991.1** Current: **$992.50** | Strength: 5/5 \u2014 Last swing low now acting as resistance; yesterday's daily high. Converg"
    },
    {
      "ts": "2026-07-23T18:08:10.244000+00:00",
      "time": "02:08 PM ET",
      "type": "alert",
      "message": "@here \ud83d\udd34 **MU \u2014 BROKE BELOW R2 $991.1** Current: **$989.50** | Strength: 5/5 \u2014 Last swing low now acting as resistance; yesterday's daily high. Converg"
    },
    {
      "ts": "2026-07-23T18:03:55.831000+00:00",
      "time": "02:03 PM ET",
      "type": "alert",
      "message": "@here \ud83d\udd34 **USO \u2014 BROKE BELOW R3 $141.89** Current: **$141.87** | Strength: 5/5 \u2014 **0.236 Fibonacci** + **swing high cluster** ($141.42, $149.47 nearby)"
    }
  ]
}