{
  "generated_at": "2026-07-15T17:06:19.012016+00:00",
  "items": [
    {
      "ts": "2026-07-15T17:04:05.907000+00:00",
      "time": "01:04 PM ET",
      "type": "analysis",
      "message": "@here \ud83d\udfe2 **NVDA \u2014 BROKE ABOVE R1 $207.65** Current: **$207.75** | Strength: 5/5 \u2014 Fibonacci 0.618 golden pocket (197.22\u2013236.54 swing), prior micro-resi"
    },
    {
      "ts": "2026-07-15T17:03:00.327000+00:00",
      "time": "01:03 PM ET",
      "type": "analysis",
      "message": "@here \ud83d\udfe2 **NVDA \u2014 BROKE ABOVE R2 $207.58** Current: **$207.62** | Strength: 5/5 Fibonacci 0.618 (golden pocket start, 189.80\u2192236.54 swing)"
    },
    {
      "ts": "2026-07-15T17:01:55.954000+00:00",
      "time": "01:01 PM ET",
      "type": "alert",
      "message": "@here \ud83d\udfe2 **SMH \u2014 BROKE ABOVE STOP $580.0** Current: **$580.51** | Strength: 5/5 Trade plan stop / invalidation level"
    },
    {
      "ts": "2026-07-15T16:51:08.145000+00:00",
      "time": "12:51 PM ET",
      "type": "analysis",
      "message": "@here \ud83d\udfe2 **COPX \u2014 BROKE ABOVE R1 $76.53** Current: **$76.61** | Strength: 5/5"
    },
    {
      "ts": "2026-07-15T16:46:51.257000+00:00",
      "time": "12:46 PM ET",
      "type": "analysis",
      "message": "@here \ud83d\udfe2 **MU \u2014 BROKE ABOVE S2 $891.66** Current: **$892.15** | Strength: 5/5 \u2014 **"
    },
    {
      "ts": "2026-07-15T16:44:41.772000+00:00",
      "time": "12:44 PM ET",
      "type": "alert",
      "message": "@here \ud83d\udfe2 **COPX \u2014 BROKE ABOVE STOP $76.3** Current: **$76.33** | Strength: 5/5 Trade plan stop / invalidation level"
    },
    {
      "ts": "2026-07-15T16:42:34.778000+00:00",
      "time": "12:42 PM ET",
      "type": "analysis",
      "message": "@here \ud83d\udfe2 **XRP \u2014 BROKE ABOVE S1 $12.4** Current: **$12.42** | Strength: 5/5 Today's low; 1H lows cluster; immediate support"
    },
    {
      "ts": "2026-07-15T16:41:28.019000+00:00",
      "time": "12:41 PM ET",
      "type": "analysis",
      "message": "@here \ud83d\udfe2 **AMD \u2014 BROKE ABOVE S1 $511.26** Current: **$511.83** | Strength: 5/5 Recent 1H support cluster ($510.5, $510.25); intraday floor"
    },
    {
      "ts": "2026-07-15T16:40:23.538000+00:00",
      "time": "12:40 PM ET",
      "type": "alert",
      "message": "@here \ud83d\udd34 **AMD \u2014 BROKE BELOW S1 $511.26** Current: **$510.98** | Strength: 5/5 Recent 1H support cluster ($510.5, $510.25); intraday floor"
    },
    {
      "ts": "2026-07-15T16:38:14.915000+00:00",
      "time": "12:38 PM ET",
      "type": "alert",
      "message": "@here \ud83d\udd34 **XRP \u2014 BROKE BELOW S1 $12.4** Current: **$12.39** | Strength: 5/5 Today's low; 1H lows cluster; immediate support"
    }
  ]
}