{
  "generated_at": "2026-05-23T19:23:58.975140+00:00",
  "portfolio_total": 866.02,
  "alpaca_equity": 505.09,
  "btc_value": 360.93,
  "cash_ready": 347.18,
  "month_pnl_pct": 10.7,
  "month_pnl_dollar": 38.6,
  "month_target_pct": 15.0,
  "unrealized_total": -17.51,
  "long_count": 2,
  "short_count": 0,
  "open": [
    {
      "ticker": "OXY",
      "side": "long",
      "entry": 55.49,
      "current": 58.81,
      "qty": 2.6851,
      "stop": 54.01,
      "tp": 61.93,
      "pnl_dollar": 8.91,
      "pnl_pct": 5.98,
      "r": 2.24,
      "conviction": "7/10",
      "status": "HOLD",
      "account": "Alpaca"
    },
    {
      "ticker": "BTC",
      "side": "long",
      "entry": 81388,
      "current": 75837,
      "qty": 0.004759,
      "stop": null,
      "tp": null,
      "pnl_dollar": -26.42,
      "pnl_pct": -6.82,
      "r": null,
      "conviction": "6/10",
      "status": "HOLD",
      "account": "Coinbase"
    }
  ]
}